hucira/__init__.py
hucira/data/20250125_cytokine_info_with_functional_classification_LV.xlsx
hucira/data/__init__.py
hucira/data/datasets.py
hucira/data/df_cips_genesets.csv
hucira/pl/__init__.py
hucira/pl/plot_communication.py
hucira/pl/plot_significant_results.py
hucira/tl/__init__.py
hucira/tl/cytokine_communication.py
hucira/tl/enrichment_test.py
hucira/tl/helper_functions.py
hucira/tl/robustness_test.py
hucira-0.1.2.dist-info/METADATA
hucira-0.1.2.dist-info/WHEEL
hucira-0.1.2.dist-info/licenses/LICENSE
hucira-0.1.2.dist-info/RECORD
