Metadata-Version: 2.4
Name: hucira
Version: 0.1.2
Summary: Human Cytokine Dictionary
Project-URL: Documentation, https://huCIRA.readthedocs.io/
Project-URL: Homepage, https://github.com/theislab/huCIRA
Project-URL: Source, https://github.com/theislab/huCIRA
Author: Jenni Liu
Maintainer-email: Jenni Liu <liu.jenni295@gmail.com>
License: MIT License
License-File: LICENSE
Classifier: Programming Language :: Python :: 3 :: Only
Classifier: Programming Language :: Python :: 3.11
Classifier: Programming Language :: Python :: 3.12
Classifier: Programming Language :: Python :: 3.13
Classifier: Programming Language :: Python :: 3.14
Requires-Python: >=3.11
Requires-Dist: anndata
Requires-Dist: bokeh
Requires-Dist: gseapy>=1.1.8
Requires-Dist: numpy>=2.1
Requires-Dist: openpyxl
Requires-Dist: pandas>=2.2.3
Requires-Dist: pycirclize
Requires-Dist: scanpy>=1.11.1
Requires-Dist: scikit-learn>=1.5.2
Requires-Dist: scipy>=1.15.2
Requires-Dist: seaborn>=0.13.2
Requires-Dist: session-info2
Requires-Dist: tqdm>=4.67.1
Provides-Extra: dev
Requires-Dist: pre-commit; extra == 'dev'
Requires-Dist: twine>=4.0.2; extra == 'dev'
Provides-Extra: doc
Requires-Dist: docutils!=0.18.*,!=0.19.*,>=0.8; extra == 'doc'
Requires-Dist: ipykernel; extra == 'doc'
Requires-Dist: ipython; extra == 'doc'
Requires-Dist: myst-nb>=1.1; extra == 'doc'
Requires-Dist: pandas; extra == 'doc'
Requires-Dist: setuptools; extra == 'doc'
Requires-Dist: sphinx-autodoc-typehints; extra == 'doc'
Requires-Dist: sphinx-book-theme>=1; extra == 'doc'
Requires-Dist: sphinx-copybutton; extra == 'doc'
Requires-Dist: sphinx-tabs; extra == 'doc'
Requires-Dist: sphinx>=8.1; extra == 'doc'
Requires-Dist: sphinxcontrib-bibtex>=1; extra == 'doc'
Requires-Dist: sphinxcontrib-katex; extra == 'doc'
Requires-Dist: sphinxext-opengraph; extra == 'doc'
Provides-Extra: test
Requires-Dist: coverage>=7.10; extra == 'test'
Requires-Dist: ipython; extra == 'test'
Requires-Dist: pytest; extra == 'test'
